imecilabt/__init__.py
imecilabt/py.typed
imecilabt/gpulab/__init__.py
imecilabt/gpulab/schemas/__init__.py
imecilabt/gpulab/schemas/active_jobs_counts.py
imecilabt/gpulab/schemas/base.py
imecilabt/gpulab/schemas/job2.py
imecilabt/gpulab/schemas/job_event.py
imecilabt/gpulab/schemas/job_filter3.py
imecilabt/gpulab/schemas/job_id.py
imecilabt/gpulab/schemas/master.py
imecilabt/gpulab/schemas/news.py
imecilabt/gpulab/schemas/slave_info2.py
imecilabt/gpulab/schemas/slave_instance.py
imecilabt/gpulab/schemas/usage_statistics.py
imecilabt/gpulab/util/__init__.py
imecilabt/gpulab/util/convert_utils.py
imecilabt/gpulab/util/docker_image.py
imecilabt/gpulab/util/enum.py
imecilabt/gpulab/util/gpulab_config.py
imecilabt/gpulab/util/gpulab_logging.py
imecilabt/gpulab/util/proxy_config.py
imecilabt/gpulab/util/serializers.py
imecilabt/gpulab/util/statistics_config.py
imecilabt/gpulab/util/validators.py
imecilabt_gpulab_common-6.0.13.dist-info/METADATA
imecilabt_gpulab_common-6.0.13.dist-info/WHEEL
imecilabt_gpulab_common-6.0.13.dist-info/licenses/LICENSE
imecilabt_gpulab_common-6.0.13.dist-info/RECORD
