Metadata-Version: 2.4
Name: imecilabt-gpulab-common
Version: 6.0.13
Summary: GPULab Common
Project-URL: HomePage, https://gpulab.ilabt.imec.be
Project-URL: Repository, https://gitlab.ilabt.imec.be/ilabt/gpulab/gpulab-common
Author-email: Thijs Walcarius <thijs.walcarius@ugent.be>, Wim Van de Meersche <wim.vandemeersche@ugent.be>, Brecht Vermeulen <brecht.vermeulen@ugent.be>
License:                     GNU GENERAL PUBLIC LICENSE
License-File: LICENSE
Classifier: Development Status :: 5 - Production/Stable
Classifier: Intended Audience :: Science/Research
Classifier: License :: OSI Approved :: GNU General Public License v3 (GPLv3)
Classifier: Operating System :: OS Independent
Classifier: Programming Language :: Python :: 3
Classifier: Programming Language :: Python :: 3.10
Classifier: Topic :: Scientific/Engineering
Requires-Python: >=3.10
Requires-Dist: imecilabt-utils<2,>=1.5.0
Requires-Dist: pydantic-settings<3,>=2.10.1
Requires-Dist: pydantic-yaml<2,>=1.5.1
Requires-Dist: pydantic[email]<3,>=2.11.7
Requires-Dist: python-dateutil
Requires-Dist: pytz
Requires-Dist: pyyaml
Requires-Dist: snakecase
